{
  "ok": true,
  "importType": "registration-roster",
  "source": {
    "sourceUrl": "https://fencing.yy-sport.com.cn/fencingapi/sigup/memberlistbytype?current=7&size=20",
    "eventCode": "RZSS2035030MEIU14",
    "sportCode": "RZSS2035030",
    "page": 7,
    "importedAt": "2026-06-09T01:47:06.865Z"
  },
  "page": {
    "current": 7,
    "size": 20,
    "total": 156
  },
  "summary": {
    "recordCount": 20,
    "sportCodes": [
      "RZSS2035030"
    ],
    "eventCodes": [
      "RZSS2035030MEIU14"
    ],
    "athleteCount": 20,
    "clubCount": 10
  },
  "normalized": {
    "records": [
      {
        "sigupId": "260436770",
        "registerType": "athlete",
        "registerId": "20140118M202410280928",
        "registerCode": "20140118M202410280928",
        "athleteName": "张锦轩",
        "birthday": "2014-01-18",
        "sex": "M",
        "sexDes": "男",
        "weapon": "E",
        "weaponDes": "重剑",
        "hand": "R",
        "sportCode": "RZSS2035030",
        "sportName": "2026年武汉击剑公开赛",
        "eventCode": "RZSS2035030MEIU14",
        "eventName": "U14男子重剑个人",
        "organCode": "JISJS0001",
        "organShortName": "江苏",
        "organName": "江苏击剑队",
        "approveStatus": "2",
        "sigupTime": "2026-05-18 14:02:25",
        "sigupPoints": "434.0",
        "sigupRank": "211",
        "regType": "0",
        "regTypeDes": "竞技",
        "dedupeKey": "sigup:260436770"
      },
      {
        "sigupId": "260436738",
        "registerType": "athlete",
        "registerId": "20120725M202103201021",
        "registerCode": "20120725M202103201021",
        "athleteName": "吴齐",
        "birthday": "2012-07-25",
        "sex": "M",
        "sexDes": "男",
        "weapon": "E",
        "weaponDes": "重剑",
        "hand": "R",
        "sportCode": "RZSS2035030",
        "sportName": "2026年武汉击剑公开赛",
        "eventCode": "RZSS2035030MEIU14",
        "eventName": "U14男子重剑个人",
        "organCode": "GUDWGSZ0001",
        "organShortName": "深圳南山万国",
        "organName": "深圳南山万国击剑俱乐部",
        "approveStatus": "2",
        "sigupTime": "2026-05-18 14:02:22",
        "sigupPoints": "1052.0",
        "sigupRank": "65",
        "regType": "1",
        "regTypeDes": "大众",
        "dedupeKey": "sigup:260436738"
      },
      {
        "sigupId": "260436747",
        "registerType": "athlete",
        "registerId": "20121008M202209221014",
        "registerCode": "20121008M202209221014",
        "athleteName": "樊浩勋",
        "birthday": "2012-10-08",
        "sex": "M",
        "sexDes": "男",
        "weapon": "E",
        "weaponDes": "重剑",
        "hand": "L",
        "sportCode": "RZSS2035030",
        "sportName": "2026年武汉击剑公开赛",
        "eventCode": "RZSS2035030MEIU14",
        "eventName": "U14男子重剑个人",
        "organCode": "ZHJZJ0001",
        "organShortName": "浙江",
        "organName": "浙江击剑队",
        "approveStatus": "2",
        "sigupTime": "2026-05-18 14:02:22",
        "sigupPoints": "3216.0",
        "sigupRank": "6",
        "regType": "0",
        "regTypeDes": "竞技",
        "dedupeKey": "sigup:260436747"
      },
      {
        "sigupId": "260436761",
        "registerType": "athlete",
        "registerId": "20141204M202306020214",
        "registerCode": "20141204M202306020214",
        "athleteName": "陈驰昊",
        "birthday": "2014-12-04",
        "sex": "M",
        "sexDes": "男",
        "weapon": "E",
        "weaponDes": "重剑",
        "hand": "L",
        "sportCode": "RZSS2035030",
        "sportName": "2026年武汉击剑公开赛",
        "eventCode": "RZSS2035030MEIU14",
        "eventName": "U14男子重剑个人",
        "organCode": "SHHSHWG0002",
        "organShortName": "上海万国",
        "organName": "上海长宁万国金剑击剑俱乐部",
        "approveStatus": "2",
        "sigupTime": "2026-05-18 14:02:22",
        "sigupPoints": "318.0",
        "sigupRank": "282",
        "regType": "1",
        "regTypeDes": "大众",
        "dedupeKey": "sigup:260436761"
      },
      {
        "sigupId": "260436762",
        "registerType": "athlete",
        "registerId": "20120726M202302080741",
        "registerCode": "20120726M202302080741",
        "athleteName": "吕泓锐",
        "birthday": "2012-07-26",
        "sex": "M",
        "sexDes": "男",
        "weapon": "E",
        "weaponDes": "重剑",
        "hand": "L",
        "sportCode": "RZSS2035030",
        "sportName": "2026年武汉击剑公开赛",
        "eventCode": "RZSS2035030MEIU14",
        "eventName": "U14男子重剑个人",
        "organCode": "GUDSZXM0001",
        "organShortName": "深圳瑞锋熊猫",
        "organName": "深圳瑞锋熊猫",
        "approveStatus": "2",
        "sigupTime": "2026-05-18 14:02:22",
        "sigupPoints": "155.0",
        "sigupRank": "482",
        "regType": "1",
        "regTypeDes": "大众",
        "dedupeKey": "sigup:260436762"
      },
      {
        "sigupId": "260436688",
        "registerType": "athlete",
        "registerId": "20131213M202211070646",
        "registerCode": "20131213M202211070646",
        "athleteName": "赵康予",
        "birthday": "2013-12-13",
        "sex": "M",
        "sexDes": "男",
        "weapon": "E",
        "weaponDes": "重剑",
        "hand": "R",
        "sportCode": "RZSS2035030",
        "sportName": "2026年武汉击剑公开赛",
        "eventCode": "RZSS2035030MEIU14",
        "eventName": "U14男子重剑个人",
        "organCode": "Empty",
        "organShortName": "个人",
        "organName": "个人会员",
        "approveStatus": "2",
        "sigupTime": "2026-05-18 14:02:15",
        "sigupPoints": "1080.0",
        "sigupRank": "58",
        "regType": "1",
        "regTypeDes": "大众",
        "dedupeKey": "sigup:260436688"
      },
      {
        "sigupId": "260436711",
        "registerType": "athlete",
        "registerId": "20130730M202107170534",
        "registerCode": "20130730M202107170534",
        "athleteName": "何牧野",
        "birthday": "2013-07-30",
        "sex": "M",
        "sexDes": "男",
        "weapon": "E",
        "weaponDes": "重剑",
        "hand": "L",
        "sportCode": "RZSS2035030",
        "sportName": "2026年武汉击剑公开赛",
        "eventCode": "RZSS2035030MEIU14",
        "eventName": "U14男子重剑个人",
        "organCode": "GUDWGSZ0001",
        "organShortName": "深圳南山万国",
        "organName": "深圳南山万国击剑俱乐部",
        "approveStatus": "2",
        "sigupTime": "2026-05-18 14:02:15",
        "sigupPoints": "1170.6",
        "sigupRank": "48",
        "regType": "1",
        "regTypeDes": "大众",
        "dedupeKey": "sigup:260436711"
      },
      {
        "sigupId": "260436712",
        "registerType": "athlete",
        "registerId": "20150205M202503170925",
        "registerCode": "20150205M202503170925",
        "athleteName": "梁哲羲",
        "birthday": "2015-02-05",
        "sex": "M",
        "sexDes": "男",
        "weapon": "E",
        "weaponDes": "重剑",
        "hand": "R",
        "sportCode": "RZSS2035030",
        "sportName": "2026年武汉击剑公开赛",
        "eventCode": "RZSS2035030MEIU14",
        "eventName": "U14男子重剑个人",
        "organCode": "XIGXGJLH0001",
        "organShortName": "香港剑乐会",
        "organName": "香港剑乐会联盟俱乐部",
        "approveStatus": "2",
        "sigupTime": "2026-05-18 14:02:15",
        "sigupPoints": "32.0",
        "sigupRank": "907",
        "regType": "1",
        "regTypeDes": "大众",
        "dedupeKey": "sigup:260436712"
      },
      {
        "sigupId": "260436680",
        "registerType": "athlete",
        "registerId": "20120910M202303211225",
        "registerCode": "20120910M202303211225",
        "athleteName": "许亦昇",
        "birthday": "2012-09-10",
        "sex": "M",
        "sexDes": "男",
        "weapon": "E",
        "weaponDes": "重剑",
        "hand": "R",
        "sportCode": "RZSS2035030",
        "sportName": "2026年武汉击剑公开赛",
        "eventCode": "RZSS2035030MEIU14",
        "eventName": "U14男子重剑个人",
        "organCode": "Empty",
        "organShortName": "个人",
        "organName": "个人会员",
        "approveStatus": "2",
        "sigupTime": "2026-05-18 14:02:10",
        "sigupPoints": "461.0",
        "sigupRank": "198",
        "regType": "1",
        "regTypeDes": "大众",
        "dedupeKey": "sigup:260436680"
      },
      {
        "sigupId": "260436635",
        "registerType": "athlete",
        "registerId": "20130408M202407060956",
        "registerCode": "20130408M202407060956",
        "athleteName": "梁諾晞",
        "birthday": "2013-04-08",
        "sex": "M",
        "sexDes": "男",
        "weapon": "E",
        "weaponDes": "重剑",
        "hand": "R",
        "sportCode": "RZSS2035030",
        "sportName": "2026年武汉击剑公开赛",
        "eventCode": "RZSS2035030MEIU14",
        "eventName": "U14男子重剑个人",
        "organCode": "GUDQTJ0001",
        "organShortName": "深圳南锋",
        "organName": "深圳南锋击剑俱乐部",
        "approveStatus": "5",
        "sigupTime": "2026-05-18 14:02:07",
        "sigupPoints": "703.0",
        "sigupRank": "130",
        "regType": "1",
        "regTypeDes": "大众",
        "dedupeKey": "sigup:260436635"
      },
      {
        "sigupId": "260436649",
        "registerType": "athlete",
        "registerId": "20130305M201909171725",
        "registerCode": "20130305M201909171725",
        "athleteName": "宫域祖",
        "birthday": "2013-03-05",
        "sex": "M",
        "sexDes": "男",
        "weapon": "E",
        "weaponDes": "重剑",
        "hand": "L",
        "sportCode": "RZSS2035030",
        "sportName": "2026年武汉击剑公开赛",
        "eventCode": "RZSS2035030MEIU14",
        "eventName": "U14男子重剑个人",
        "organCode": "GUDWGSZ0001",
        "organShortName": "深圳南山万国",
        "organName": "深圳南山万国击剑俱乐部",
        "approveStatus": "2",
        "sigupTime": "2026-05-18 14:02:07",
        "sigupPoints": "936.0",
        "sigupRank": "83",
        "regType": "3",
        "regTypeDes": "竞技*",
        "dedupeKey": "sigup:260436649"
      },
      {
        "sigupId": "260436654",
        "registerType": "athlete",
        "registerId": "20131101M202104080704",
        "registerCode": "20131101M202104080704",
        "athleteName": "陈奕亦",
        "birthday": "2013-11-01",
        "sex": "M",
        "sexDes": "男",
        "weapon": "E",
        "weaponDes": "重剑",
        "hand": "R",
        "sportCode": "RZSS2035030",
        "sportName": "2026年武汉击剑公开赛",
        "eventCode": "RZSS2035030MEIU14",
        "eventName": "U14男子重剑个人",
        "organCode": "GUDWGSZ0001",
        "organShortName": "深圳南山万国",
        "organName": "深圳南山万国击剑俱乐部",
        "approveStatus": "2",
        "sigupTime": "2026-05-18 14:02:07",
        "sigupPoints": "1248.6",
        "sigupRank": "40",
        "regType": "1",
        "regTypeDes": "大众",
        "dedupeKey": "sigup:260436654"
      },
      {
        "sigupId": "260436571",
        "registerType": "athlete",
        "registerId": "20120710M202401291128",
        "registerCode": "20120710M202401291128",
        "athleteName": "梁尚智",
        "birthday": "2012-07-10",
        "sex": "M",
        "sexDes": "男",
        "weapon": "E",
        "weaponDes": "重剑",
        "hand": "R",
        "sportCode": "RZSS2035030",
        "sportName": "2026年武汉击剑公开赛",
        "eventCode": "RZSS2035030MEIU14",
        "eventName": "U14男子重剑个人",
        "organCode": "GUDQTJ0001",
        "organShortName": "深圳南锋",
        "organName": "深圳南锋击剑俱乐部",
        "approveStatus": "2",
        "sigupTime": "2026-05-18 14:02:00",
        "sigupPoints": "718.0",
        "sigupRank": "128",
        "regType": "1",
        "regTypeDes": "大众",
        "dedupeKey": "sigup:260436571"
      },
      {
        "sigupId": "260436561",
        "registerType": "athlete",
        "registerId": "20140831M202304120455",
        "registerCode": "20140831M202304120455",
        "athleteName": "何适",
        "birthday": "2014-08-31",
        "sex": "M",
        "sexDes": "男",
        "weapon": "E",
        "weaponDes": "重剑",
        "hand": "R",
        "sportCode": "RZSS2035030",
        "sportName": "2026年武汉击剑公开赛",
        "eventCode": "RZSS2035030MEIU14",
        "eventName": "U14男子重剑个人",
        "organCode": "HUBYSJLH0001",
        "organShortName": "湖北永尚",
        "organName": "湖北永尚剑乐会国际击剑中心",
        "approveStatus": "5",
        "sigupTime": "2026-05-18 14:01:55",
        "sigupPoints": "28.0",
        "sigupRank": "971",
        "regType": "1",
        "regTypeDes": "大众",
        "dedupeKey": "sigup:260436561"
      },
      {
        "sigupId": "260436562",
        "registerType": "athlete",
        "registerId": "20120727M202208070356",
        "registerCode": "20120727M202208070356",
        "athleteName": "胡凯博",
        "birthday": "2012-07-27",
        "sex": "M",
        "sexDes": "男",
        "weapon": "E",
        "weaponDes": "重剑",
        "hand": "L",
        "sportCode": "RZSS2035030",
        "sportName": "2026年武汉击剑公开赛",
        "eventCode": "RZSS2035030MEIU14",
        "eventName": "U14男子重剑个人",
        "organCode": "GUDYGJJ0001",
        "organShortName": "广州阳光剑匠",
        "organName": "广州阳光剑匠击剑工作室",
        "approveStatus": "2",
        "sigupTime": "2026-05-18 14:01:55",
        "sigupPoints": "1356.0",
        "sigupRank": "36",
        "regType": "1",
        "regTypeDes": "大众",
        "dedupeKey": "sigup:260436562"
      },
      {
        "sigupId": "260436518",
        "registerType": "athlete",
        "registerId": "20120208M202103271059",
        "registerCode": "20120208M202103271059",
        "athleteName": "常皓博",
        "birthday": "2012-02-08",
        "sex": "M",
        "sexDes": "男",
        "weapon": "E",
        "weaponDes": "重剑",
        "hand": "R",
        "sportCode": "RZSS2035030",
        "sportName": "2026年武汉击剑公开赛",
        "eventCode": "RZSS2035030MEIU14",
        "eventName": "U14男子重剑个人",
        "organCode": "HUBYSJLH0001",
        "organShortName": "湖北永尚",
        "organName": "湖北永尚剑乐会国际击剑中心",
        "approveStatus": "2",
        "sigupTime": "2026-05-18 14:01:52",
        "sigupPoints": "1090.0",
        "sigupRank": "55",
        "regType": "1",
        "regTypeDes": "大众",
        "dedupeKey": "sigup:260436518"
      },
      {
        "sigupId": "260436470",
        "registerType": "athlete",
        "registerId": "20130730M202111241127",
        "registerCode": "20130730M202111241127",
        "athleteName": "林梓乔",
        "birthday": "2013-07-30",
        "sex": "M",
        "sexDes": "男",
        "weapon": "E",
        "weaponDes": "重剑",
        "hand": "L",
        "sportCode": "RZSS2035030",
        "sportName": "2026年武汉击剑公开赛",
        "eventCode": "RZSS2035030MEIU14",
        "eventName": "U14男子重剑个人",
        "organCode": "GUDWGSZ0001",
        "organShortName": "深圳南山万国",
        "organName": "深圳南山万国击剑俱乐部",
        "approveStatus": "2",
        "sigupTime": "2026-05-18 14:01:45",
        "sigupPoints": "984.0",
        "sigupRank": "74",
        "regType": "1",
        "regTypeDes": "大众",
        "dedupeKey": "sigup:260436470"
      },
      {
        "sigupId": "260436483",
        "registerType": "athlete",
        "registerId": "20140522M202402270430",
        "registerCode": "20140522M202402270430",
        "athleteName": "傅衍心",
        "birthday": "2014-05-22",
        "sex": "M",
        "sexDes": "男",
        "weapon": "E",
        "weaponDes": "重剑",
        "hand": "R",
        "sportCode": "RZSS2035030",
        "sportName": "2026年武汉击剑公开赛",
        "eventCode": "RZSS2035030MEIU14",
        "eventName": "U14男子重剑个人",
        "organCode": "XIGXGJLH0001",
        "organShortName": "香港剑乐会",
        "organName": "香港剑乐会联盟俱乐部",
        "approveStatus": "2",
        "sigupTime": "2026-05-18 14:01:45",
        "sigupPoints": "174.0",
        "sigupRank": "452",
        "regType": "1",
        "regTypeDes": "大众",
        "dedupeKey": "sigup:260436483"
      },
      {
        "sigupId": "260436437",
        "registerType": "athlete",
        "registerId": "20130428M202311090327",
        "registerCode": "20130428M202311090327",
        "athleteName": "梁力文",
        "birthday": "2013-04-28",
        "sex": "M",
        "sexDes": "男",
        "weapon": "E",
        "weaponDes": "重剑",
        "hand": "R",
        "sportCode": "RZSS2035030",
        "sportName": "2026年武汉击剑公开赛",
        "eventCode": "RZSS2035030MEIU14",
        "eventName": "U14男子重剑个人",
        "organCode": "GUDQTJ0001",
        "organShortName": "深圳南锋",
        "organName": "深圳南锋击剑俱乐部",
        "approveStatus": "2",
        "sigupTime": "2026-05-18 14:01:40",
        "sigupPoints": "378.8",
        "sigupRank": "245",
        "regType": "1",
        "regTypeDes": "大众",
        "dedupeKey": "sigup:260436437"
      },
      {
        "sigupId": "260436446",
        "registerType": "athlete",
        "registerId": "20130910M202306210455",
        "registerCode": "20130910M202306210455",
        "athleteName": "王于果",
        "birthday": "2013-09-10",
        "sex": "M",
        "sexDes": "男",
        "weapon": "E",
        "weaponDes": "重剑",
        "hand": "R",
        "sportCode": "RZSS2035030",
        "sportName": "2026年武汉击剑公开赛",
        "eventCode": "RZSS2035030MEIU14",
        "eventName": "U14男子重剑个人",
        "organCode": "ZHJZJ0001",
        "organShortName": "浙江",
        "organName": "浙江击剑队",
        "approveStatus": "2",
        "sigupTime": "2026-05-18 14:01:40",
        "sigupPoints": "806.0",
        "sigupRank": "110",
        "regType": "0",
        "regTypeDes": "竞技",
        "dedupeKey": "sigup:260436446"
      }
    ]
  }
}