{
  "ok": true,
  "importType": "registration-roster",
  "source": {
    "sourceUrl": "https://fencing.yy-sport.com.cn/fencingapi/sigup/memberlistbytype?current=1&size=20",
    "eventCode": "RZSSSAN0120260612METU10",
    "sportCode": "RZSSSAN0120260612",
    "page": 1,
    "importedAt": "2026-06-09T01:50:53.407Z"
  },
  "page": {
    "current": 1,
    "size": 20,
    "total": 5
  },
  "summary": {
    "recordCount": 5,
    "sportCodes": [
      "RZSSSAN0120260612"
    ],
    "eventCodes": [
      "RZSSSAN0120260612METU10"
    ],
    "athleteCount": 0,
    "clubCount": 3
  },
  "normalized": {
    "records": [
      {
        "sigupId": "258994107",
        "registerType": "team",
        "registerId": "RZSSSAN0120260612METU10_103_OTQYK",
        "registerCode": null,
        "athleteName": "",
        "birthday": null,
        "sex": null,
        "sexDes": null,
        "weapon": null,
        "weaponDes": null,
        "hand": null,
        "sportCode": "RZSSSAN0120260612",
        "sportName": "2026年西安市\"万河荟″杯Rapier击剑公开赛",
        "eventCode": "RZSSSAN0120260612METU10",
        "eventName": "U10男子重剑团体",
        "organCode": "TIJTJTW0001",
        "organShortName": "天津智桥",
        "organName": "天津智桥击剑俱乐部",
        "approveStatus": "2",
        "sigupTime": "2026-05-27 13:35:26",
        "sigupPoints": null,
        "sigupRank": null,
        "regType": null,
        "regTypeDes": null,
        "dedupeKey": "sigup:258994107"
      },
      {
        "sigupId": "258994093",
        "registerType": "team",
        "registerId": "RZSSSAN0120260612METU10_600_VNUGL",
        "registerCode": null,
        "athleteName": "",
        "birthday": null,
        "sex": null,
        "sexDes": null,
        "weapon": null,
        "weaponDes": null,
        "hand": null,
        "sportCode": "RZSSSAN0120260612",
        "sportName": "2026年西安市\"万河荟″杯Rapier击剑公开赛",
        "eventCode": "RZSSSAN0120260612METU10",
        "eventName": "U10男子重剑团体",
        "organCode": "SHAXAYT0001",
        "organShortName": "西安倚天",
        "organName": "西安倚天国际击剑俱乐部",
        "approveStatus": "2",
        "sigupTime": "2026-05-21 13:52:51",
        "sigupPoints": null,
        "sigupRank": null,
        "regType": null,
        "regTypeDes": null,
        "dedupeKey": "sigup:258994093"
      },
      {
        "sigupId": "258994085",
        "registerType": "team",
        "registerId": "RZSSSAN0120260612METU10_623_GZBVB",
        "registerCode": null,
        "athleteName": "",
        "birthday": null,
        "sex": null,
        "sexDes": null,
        "weapon": null,
        "weaponDes": null,
        "hand": null,
        "sportCode": "RZSSSAN0120260612",
        "sportName": "2026年西安市\"万河荟″杯Rapier击剑公开赛",
        "eventCode": "RZSSSAN0120260612METU10",
        "eventName": "U10男子重剑团体",
        "organCode": "SHAXAWG0001",
        "organShortName": "西安万国",
        "organName": "西安万国击剑俱乐部",
        "approveStatus": "2",
        "sigupTime": "2026-05-19 14:53:54",
        "sigupPoints": null,
        "sigupRank": null,
        "regType": null,
        "regTypeDes": null,
        "dedupeKey": "sigup:258994085"
      },
      {
        "sigupId": "258994077",
        "registerType": "team",
        "registerId": "RZSSSAN0120260612MSTU12_623_BHFCW",
        "registerCode": null,
        "athleteName": "",
        "birthday": null,
        "sex": null,
        "sexDes": null,
        "weapon": null,
        "weaponDes": null,
        "hand": null,
        "sportCode": "RZSSSAN0120260612",
        "sportName": "2026年西安市\"万河荟″杯Rapier击剑公开赛",
        "eventCode": "RZSSSAN0120260612METU10",
        "eventName": "U10男子重剑团体",
        "organCode": "SHAXAWG0001",
        "organShortName": "西安万国",
        "organName": "西安万国击剑俱乐部",
        "approveStatus": "2",
        "sigupTime": "2026-05-18 15:31:12",
        "sigupPoints": null,
        "sigupRank": null,
        "regType": null,
        "regTypeDes": null,
        "dedupeKey": "sigup:258994077"
      },
      {
        "sigupId": "258994067",
        "registerType": "team",
        "registerId": "RZSSSAN0120260612METU10_623_USCJV",
        "registerCode": null,
        "athleteName": "",
        "birthday": null,
        "sex": null,
        "sexDes": null,
        "weapon": null,
        "weaponDes": null,
        "hand": null,
        "sportCode": "RZSSSAN0120260612",
        "sportName": "2026年西安市\"万河荟″杯Rapier击剑公开赛",
        "eventCode": "RZSSSAN0120260612METU10",
        "eventName": "U10男子重剑团体",
        "organCode": "SHAXAWG0001",
        "organShortName": "西安万国",
        "organName": "西安万国击剑俱乐部",
        "approveStatus": "2",
        "sigupTime": "2026-05-18 14:08:29",
        "sigupPoints": null,
        "sigupRank": null,
        "regType": null,
        "regTypeDes": null,
        "dedupeKey": "sigup:258994067"
      }
    ]
  }
}